otfpythonpkg/__init__.py
otfpythonpkg/aws/__init__.py
otfpythonpkg/aws/aws.py
otfpythonpkg/db/MySQL.py
otfpythonpkg/db/Snowflake.py
otfpythonpkg/db/__init__.py
otfpythonpkg/utils/__init__.py
otfpythonpkg/utils/util.py
otfpythonpkg-0.2.0.dist-info/METADATA
otfpythonpkg-0.2.0.dist-info/WHEEL
otfpythonpkg-0.2.0.dist-info/top_level.txt
otfpythonpkg-0.2.0.dist-info/RECORD
